guarana/__init__.py
guarana/schemas/base.py
guarana/schemas/customer.py
guarana/schemas/events.py
guarana/schemas/order.py
guarana/segment_client.py
guarana/trackers/customer_tracker.py
guarana/trackers/order_tracker.py
guarana-2.4.4.dist-info/WHEEL
guarana-2.4.4.dist-info/METADATA
guarana-2.4.4.dist-info/RECORD
