Metadata-Version: 2.1
Name: guarana
Version: 2.4.4
Summary: 
Author: Rodrigo Godinho
Author-email: rodrigolegod@gmail.com
Requires-Python: >=3.10,<4.0
Classifier: Programming Language :: Python :: 3
Classifier: Programming Language :: Python :: 3.10
Requires-Dist: loguru (>=0.6.0,<0.7.0)
Requires-Dist: pydantic (>=1.10.2,<2.0.0)
Requires-Dist: segment-analytics-python (>=2.2.0,<3.0.0)
